Workbook
Name aporte: Ferramenta!$D$21
Name patrimonio: Ferramenta!$D$24
Name qtd_anos: Ferramenta!$D$22
Name rendimento_carteira: Ferramenta!$D$16
Name salario: Ferramenta!$D$15
Name sujestao_investimento: Ferramenta!$D$17
Name taxa_mensal: Ferramenta!$D$23

Sheet Ferramenta
B11: SIMULADOR DE INVESTIMENTOS FII
B14: CONFIGURAÇÕES
B15: Salário | D15: 2000
B16: Rendimento Carteira | D16: 0.006
B17: Sujestão Investimento (30%) | D17: =D15*30% -> 600
B20: INVESTIMENTO MENSAL
B21: Quanto investir por mês? | D21: 200
B22: Por quantos anos? | D22: 5
B23: Taxa de rendimento mensal? | D23: 0.01079
B24: Patrimônio acumulado? | D24: =FV(taxa_mensal,qtd_anos*12,aporte*-1) -> 16755.383
B25: Dividendos mensais? | D25: =patrimonio*rendimento_carteira -> 100.5323
B28: CENÁRIOS | D28: DIVIDENDOS
A29: 2 | B29: Quanto em 2 anos? | C29: =FV($D$23,$A29*12,$D$21*-1) -> 5445.5255 | D29: =C29*rendimento_carteira -> 32.673153
A30: 5 | B30: Quanto em 5 anos? | C30: =FV($D$23,$A30*12,$D$21*-1) -> 16755.383 | D30: =C30*rendimento_carteira -> 100.5323
A31: 10 | B31: Quanto em 10 anos? | C31: =FV($D$23,$A31*12,$D$21*-1) -> 48656.843 | D31: =C31*rendimento_carteira -> 291.94106
A32: 20 | B32: Quanto em 20 anos? | C32: =FV($D$23,$A32*12,$D$21*-1) -> 225039.68 | D32: =C32*rendimento_carteira -> 1350.2381
A33: 30 | B33: Quanto em 30 anos? | C33: =FV($D$23,$A33*12,$D$21*-1) -> 864433.93 | D33: =C33*rendimento_carteira -> 5186.6036
B36: Perfil | C36: CONSERVADOR
B37: Valor a ser investido por mês | C37: =aporte -> 200
B39: TIPO DE FII | C39: Percentual sugerido | D39: Valores
B40: PAPEL | C40: =VLOOKUP($C$36&"-"&B40,Apoio!B12:E30,4,FALSE) -> 0.3 | D40: =C40*$C$37 -> 60
B41: TIJOLO | C41: =VLOOKUP($C$36&"-"&B41,Apoio!B13:E31,4,FALSE) -> 0.5 | D41: =C41*$C$37 -> 100
B42: HÍBRIDOS | C42: =VLOOKUP($C$36&"-"&B42,Apoio!B14:E32,4,FALSE) -> 0.1 | D42: =C42*$C$37 -> 20
B43: FOFs | C43: =VLOOKUP($C$36&"-"&B43,Apoio!B15:E33,4,FALSE) -> 0.1 | D43: =C43*$C$37 -> 20
B44: DESENVOLVIMENTO | C44: =VLOOKUP($C$36&"-"&B44,Apoio!B16:E34,4,FALSE) -> 0 | D44: =C44*$C$37 -> 0
B45: HOTELARIAS | C45: =VLOOKUP($C$36&"-"&B45,Apoio!B17:E35,4,FALSE) -> 0 | D45: =C45*$C$37 -> 0
D46: =SUM(D40:D45) -> 200

Sheet Apoio
B2: Tabela Comparativa de Tipos de FIIs
B3: Tipo de Fundo | C3: Ativos Principais | D3: Fontes de Renda | E3: Exemplos (Códigos)
B4: Tijolo | C4: Imóveis Físicos (Shoppings, Galpões, Lajes Corporativas) | D4: Aluguéis, Venda de Imóveis | E4: HGLG11, XPML11, BRCO11
B5: Papel | C5: Certificados de Recebíveis Imobiliários (CRIs, LCIs, LHs) | D5: Juros e Correção Monetária (IPCA/CDI) | E5: KNCR11, IRDM11, BCRI11
B6: Híbrido | C6: Mix de Tijolo (Imóveis) e Papel (Recebíveis) | D6: Aluguéis + Juros/Inflação | E6: Combinação dos dois
B7: Fundo de Fundos (FoFs) | C7: Cotas de outros FIIs, CRIs, LCIs | D7: Rendimentos de outros Fundos | E7: BCFF11, HFOF11
B8: Desenvolvimento | C8: Terrenos, Imóveis em Construção | D8: Venda de Imóveis Novos | E8: (Menos comuns, foco em lucro da obra)
B9: Fiagro | C9: Certificados de Recebíveis do Agronegócio (CRAs) | D9: Juros/Inflação do Agronegócio | E9: BTAL11 (exemplo Agro)
B12: CHAVE | C12: PERFIL | D12: TIPO DE FII | E12: %
B13: =C13&"-"&D13 -> CONSERVADOR-PAPEL | C13: CONSERVADOR | D13: PAPEL | E13: 0.3
B14: =C14&"-"&D14 -> CONSERVADOR-TIJOLO | C14: CONSERVADOR | D14: TIJOLO | E14: 0.5
B15: =C15&"-"&D15 -> CONSERVADOR-HÍBRIDOS | C15: CONSERVADOR | D15: HÍBRIDOS | E15: 0.1
B16: =C16&"-"&D16 -> CONSERVADOR-FOFs | C16: CONSERVADOR | D16: FOFs | E16: 0.1
B17: =C17&"-"&D17 -> CONSERVADOR-DESENVOLVIMENTO | C17: CONSERVADOR | D17: DESENVOLVIMENTO | E17: 0
B18: =C18&"-"&D18 -> CONSERVADOR-HOTELARIAS | C18: CONSERVADOR | D18: HOTELARIAS | E18: 0
B19: =C19&"-"&D19 -> MODERADO-PAPEL | C19: MODERADO | D19: PAPEL | E19: 0.32
B20: =C20&"-"&D20 -> MODERADO-TIJOLO | C20: MODERADO | D20: TIJOLO | E20: 0.35
B21: =C21&"-"&D21 -> MODERADO-HÍBRIDOS | C21: MODERADO | D21: HÍBRIDOS | E21: 0.08
B22: =C22&"-"&D22 -> MODERADO-FOFs | C22: MODERADO | D22: FOFs | E22: 0.05
B23: =C23&"-"&D23 -> MODERADO-DESENVOLVIMENTO | C23: MODERADO | D23: DESENVOLVIMENTO | E23: 0.1
B24: =C24&"-"&D24 -> MODERADO-HOTELARIAS | C24: MODERADO | D24: HOTELARIAS | E24: 0.1
... B30: =C30&"-"&D30 -> AGRESSIVO-HOTELARIAS | C30: AGRESSIVO | D30: HOTELARIAS | E30: 0.1
